LICENSE
MANIFEST.in
README.md
VERSION.txt
setup.cfg
setup.py
ckanext/__init__.py
ckanext/upload_via_email/__init__.py
ckanext/upload_via_email/plugin.py
ckanext/upload_via_email/pipelines/__init__.py
ckanext/upload_via_email/pipelines/add_ckan_allowed_senders_resource.py
ckanext/upload_via_email/pipelines/download_messages.py
ckanext/upload_via_email/pipelines/get_datasets_package.py
ckanext/upload_via_email/pipelines/pipeline-spec.yaml
ckanext/upload_via_email/pipelines/requirements.txt
ckanext/upload_via_email/pipelines/update_created_datasets.py
ckanext/upload_via_email/pipelines/utils.py
ckanext/upload_via_email/tests/__init__.py
ckanext/upload_via_email/tests/test_plugin.py
ckanext_upload_via_email.egg-info/PKG-INFO
ckanext_upload_via_email.egg-info/SOURCES.txt
ckanext_upload_via_email.egg-info/dependency_links.txt
ckanext_upload_via_email.egg-info/entry_points.txt
ckanext_upload_via_email.egg-info/namespace_packages.txt
ckanext_upload_via_email.egg-info/top_level.txt