Metadata-Version: 1.1
Name: ckanext-upload-via-email
Version: 0.1.5
Summary: Upload packages to CKAN via Email
Home-page: https://github.com/OriHoch/ckanext-upload_via_email
Author: Ori Hoch
Author-email: ori@uumpa.com
License: AGPL
Keywords: CKAN file upload email
Platform: UNKNOWN
Classifier: Development Status :: 4 - Beta
Classifier: License :: OSI Approved :: GNU Affero General Public License v3 or later (AGPLv3+)
Classifier: Programming Language :: Python :: 2.7
